Metadata-Version: 1.0
Name: amerdistribution
Version: 0.2
Summary: Gaussian and Binomial distributions
Home-page: UNKNOWN
Author: Amer
Author-email: amer.deraa@gmail.com
License: UNKNOWN
Platform: UNKNOWN
